tests/__init__.py
tests/topics/__init__.py
tests/topics/test_unit_testing.py
pygoul-0.0.3.dist-info/LICENSE
pygoul-0.0.3.dist-info/METADATA
pygoul-0.0.3.dist-info/WHEEL
pygoul-0.0.3.dist-info/top_level.txt
pygoul-0.0.3.dist-info/RECORD
