Metadata-Version: 2.1
Name: pygoul
Version: 0.0.3
Summary: A goul library
Home-page: https://github.com/goulchen/PyGoul
Author: Goulc'hen
Author-email: goulmeur@gmail.com
License: UNKNOWN
Platform: UNKNOWN
Classifier: Programming Language :: Python :: 3
Classifier: License :: OSI Approved :: MIT License
Classifier: Operating System :: OS Independent
Requires-Python: >=3.6
